MANIFEST.in
README.md
setup.py
crypton/__init__.py
crypton/crypton.py
crypton/errors.py
crypton.egg-info/PKG-INFO
crypton.egg-info/SOURCES.txt
crypton.egg-info/dependency_links.txt
crypton.egg-info/entry_points.txt
crypton.egg-info/requires.txt
crypton.egg-info/top_level.txt
crypton/cli/__init__.py
crypton/cli/cli.py
crypton/cli/cli_asymmetric.py
crypton/cli/cli_dsa.py
crypton/cli/cli_ecdsa.py
crypton/cli/cli_ed25519.py
crypton/cli/cli_hash.py
crypton/cli/cli_rsa.py
crypton/cli/cli_symmetric.py
crypton/cli/cli_x25519.py
crypton/cli/cli_x509.py
crypton/crypt_algorithms/__init__.py
crypton/crypt_algorithms/asymmetric/X509.py
crypton/crypt_algorithms/asymmetric/__init__.py
crypton/crypt_algorithms/asymmetric/dsa.py
crypton/crypt_algorithms/asymmetric/ecdsa.py
crypton/crypt_algorithms/asymmetric/ed25519.py
crypton/crypt_algorithms/asymmetric/rsa.py
crypton/crypt_algorithms/asymmetric/x25519.py
crypton/crypt_algorithms/hash/__init__.py
crypton/crypt_algorithms/hash/sha2.py
crypton/crypt_algorithms/hash/sha3.py
crypton/crypt_algorithms/password/__init__.py
crypton/crypt_algorithms/password/check.py
crypton/crypt_algorithms/password/generate.py
crypton/crypt_algorithms/password/wordlist.txt
crypton/crypt_algorithms/symmetric/__init__.py
crypton/crypt_algorithms/symmetric/aes.py
crypton/modes/__init__.py
crypton/modes/command_line.py
crypton/modes/interactive_mode.py