Metadata-Version: 2.1
Name: crypton
Version: 1.0.0
Summary: UNKNOWN
Home-page: https://github.com/OverwatchHeir/CryptOn.git
Author: OverwatchHeir
Author-email: softw.dev@protonmail.com
License: GNU
Download-URL: https://github.com/OverwatchHeir/CryptOn/archive/master.zip
Platform: UNKNOWN
Classifier: Topic :: Utilities
Classifier: Natural Language :: English
Classifier: Programming Language :: Python :: 3.7
